sinacor_negs/__init__.py
sinacor_negs/negs.py
sinacor_negs/reader.py
sinacor_negs/utils.py
sinacor_negs-0.1.2.dist-info/LICENSE.txt
sinacor_negs-0.1.2.dist-info/METADATA
sinacor_negs-0.1.2.dist-info/WHEEL
sinacor_negs-0.1.2.dist-info/RECORD
