Metadata-Version: 2.1
Name: sinacor-negs
Version: 0.1.2
Summary: Leitor do arquivo NEGS.txt da B3 (Sinacor)
Home-page: https://github.com/renanmoretto/sinacor_negs
License: MIT
Author: renanmoretto
Author-email: himynameisrenan@outlook.com
Requires-Python: >=3.11,<4.0
Classifier: License :: OSI Approved :: MIT License
Classifier: Programming Language :: Python :: 3
Classifier: Programming Language :: Python :: 3.11
Requires-Dist: numpy (>=1.24.2,<2.0.0)
Requires-Dist: pandas (>=2.0.0,<3.0.0)
Project-URL: Repository, https://github.com/renanmoretto/sinacor_negs
